{
    "readelf.txt": {
        "modified": "2010-03-01 10:25:20",
        "size": "7.48KB",
        "md5": "7178da53c91271c817430e2659d1b29f",
        "sha256": "5ecb74e51c6f979bd95259b546ab1465890768ddff56c5ce1b4ab268b6fc1e32"
    },
    "Metadata": {
        "Content-Encoding": "ISO-8859-1",
        "Content-Type": "text/plain; charset=ISO-8859-1",
        "X-Parsed-By": [
            "org.apache.tika.parser.DefaultParser",
            "org.apache.tika.parser.csv.TextAndCSVParser"
        ],
        "X-TIKA:content_handler": "ToTextContentHandler",
        "X-TIKA:embedded_depth": "0",
        "X-TIKA:parse_time_millis": "1",
        "resourceName": "b'readelf.txt'"
    }
}