{
    "dj.prise1.15k.aifc.raw.aiff.aifc,v": {
        "modified": "2003-06-05 16:39:51",
        "size": "38.63KB",
        "md5": "3c5bf00d8e5a330e87fe3bee4d8e1ceb",
        "sha256": "1b501179eab56830519b40547916dc7b69467870c228720b3405a4f727bf9f84"
    },
    "Metadata": {
        "Content-Type": "application/octet-stream",
        "X-Parsed-By": "org.apache.tika.parser.EmptyParser",
        "X-TIKA:embedded_depth": "0",
        "X-TIKA:parse_time_millis": "1",
        "resourceName": "b'dj.prise1.15k.aifc.raw.aiff.aifc,v'"
    }
}