{
    "Tent_SCENE.o,v": {
        "modified": "2003-10-10 23:31:26",
        "size": "3.73KB",
        "md5": "e48c180db7d09af56be21c111dab7eec",
        "sha256": "aa752420ff80c87743dbec1cfe3bde19ed5b528909b5e8948d509a4aab0aa55d"
    },
    "Metadata": {
        "Content-Type": "application/octet-stream",
        "X-Parsed-By": "org.apache.tika.parser.EmptyParser",
        "X-TIKA:embedded_depth": "0",
        "X-TIKA:parse_time_millis": "0",
        "resourceName": "b'Tent_SCENE.o,v'"
    }
}