{
    "bl_div.v,v": {
        "modified": "2002-10-29 01:03:30",
        "size": "8.56KB",
        "md5": "beffc28f554947008508f57aa662c548",
        "sha256": "17083768444cd830527f35b8dc4e5f08f52f80f86abc38ab894a4889a31bcf5a"
    },
    "Metadata": {
        "Content-Encoding": "ISO-8859-1",
        "Content-Type": "text/plain; charset=ISO-8859-1",
        "X-Parsed-By": [
            "org.apache.tika.parser.DefaultParser",
            "org.apache.tika.parser.csv.TextAndCSVParser"
        ],
        "X-TIKA:content_handler": "ToTextContentHandler",
        "X-TIKA:embedded_depth": "0",
        "X-TIKA:parse_time_millis": "0",
        "resourceName": "b'bl_div.v,v'"
    }
}