{
    "dj.rankdown.3rd.16k.aifc,v": {
        "modified": "2003-10-10 23:12:19",
        "size": "12.29KB",
        "md5": "34f3d5956c1c800e2c57b9d39b1145fc",
        "sha256": "751fbd164f60722b06e976b442afb8017a75dbbc438591183654ff0c5e19aa6d"
    },
    "Metadata": {
        "Content-Type": "application/octet-stream",
        "X-Parsed-By": "org.apache.tika.parser.EmptyParser",
        "X-TIKA:embedded_depth": "0",
        "X-TIKA:parse_time_millis": "0",
        "resourceName": "b'dj.rankdown.3rd.16k.aifc,v'"
    }
}