{
    "ef_warau.rel,v": {
        "modified": "2003-03-19 00:47:07",
        "size": "0.86KB",
        "md5": "e9636da402882c542af693a8dfee8382",
        "sha256": "c0f796237131f70d0128a6c82fa3cac011b8f00e984e04967ba8ca90b3f0437d"
    },
    "Metadata": {
        "Content-Type": "application/octet-stream",
        "X-Parsed-By": "org.apache.tika.parser.EmptyParser",
        "X-TIKA:embedded_depth": "0",
        "X-TIKA:parse_time_millis": "1",
        "resourceName": "b'ef_warau.rel,v'"
    }
}