{
    "object_kon_isu.szs,v": {
        "modified": "2003-03-19 00:47:21",
        "size": "1.48KB",
        "md5": "9c5cdca5bb451f7333b5e1339dee977d",
        "sha256": "031aeff2dae689c77fe06d092835a00b0c21118b4283b980e7bc47b7209487ca"
    },
    "Metadata": {
        "Content-Type": "application/octet-stream",
        "X-Parsed-By": "org.apache.tika.parser.EmptyParser",
        "X-TIKA:embedded_depth": "0",
        "X-TIKA:parse_time_millis": "0",
        "resourceName": "b'object_kon_isu.szs,v'"
    }
}