{
    "amfield.c,v": {
        "modified": "2006-02-23 14:38:58",
        "size": "8.26KB",
        "md5": "10dbfcd97878bd5dab643807227dabc4",
        "sha256": "5f54330829966fa4682f5eb3f3d36c568e7fa925742310ef3613278ec4b27a3b"
    },
    "Metadata": {
        "Content-Encoding": "ISO-8859-1",
        "Content-Type": "text/plain; charset=ISO-8859-1",
        "X-Parsed-By": [
            "org.apache.tika.parser.DefaultParser",
            "org.apache.tika.parser.csv.TextAndCSVParser"
        ],
        "X-TIKA:content_handler": "ToTextContentHandler",
        "X-TIKA:embedded_depth": "0",
        "X-TIKA:parse_time_millis": "1",
        "resourceName": "b'amfield.c,v'"
    }
}