{
    ".IPTcp.d": {
        "modified": "2009-05-05 11:14:39",
        "size": "1.34KB",
        "md5": "af29597750a044d83294b8461b40bf3a",
        "sha256": "69617a51c3a6f59e42e4dce0d77cec093e865c8763e73a6c671884cdf5a3e541"
    },
    "Metadata": {
        "Content-Encoding": "ISO-8859-1",
        "Content-Type": "text/plain; charset=ISO-8859-1",
        "X-Parsed-By": [
            "org.apache.tika.parser.DefaultParser",
            "org.apache.tika.parser.csv.TextAndCSVParser"
        ],
        "X-TIKA:content_handler": "ToTextContentHandler",
        "X-TIKA:embedded_depth": "0",
        "X-TIKA:parse_time_millis": "0",
        "resourceName": "b'.IPTcp.d'"
    }
}