{
    "odom.P3D,v": {
        "modified": "2004-03-05 15:18:38",
        "size": "25.19KB",
        "md5": "27ba03663d00a902bf7e7804c05ac3ab",
        "sha256": "729f45f642f205607efa6831fa13834427116ff8a063563dacb6607a6462ecb4"
    },
    "Metadata": {
        "Content-Type": "application/octet-stream",
        "X-Parsed-By": "org.apache.tika.parser.EmptyParser",
        "X-TIKA:embedded_depth": "0",
        "X-TIKA:parse_time_millis": "1",
        "resourceName": "b'odom.P3D,v'"
    }
}