{
    ".es_title.d": {
        "modified": "2008-02-19 14:40:53",
        "size": "1.28KB",
        "md5": "1e731ca518ba7c6970705035466df993",
        "sha256": "80792e40a083b90c0d33fe23bdd4b050ca06c94023e80291dbe5da5b786e6733"
    },
    "Metadata": {
        "Content-Encoding": "ISO-8859-1",
        "Content-Type": "text/plain; charset=ISO-8859-1",
        "X-Parsed-By": [
            "org.apache.tika.parser.DefaultParser",
            "org.apache.tika.parser.csv.TextAndCSVParser"
        ],
        "X-TIKA:content_handler": "ToTextContentHandler",
        "X-TIKA:embedded_depth": "0",
        "X-TIKA:parse_time_millis": "1",
        "resourceName": "b'.es_title.d'"
    }
}