{
    "headers.h,v": {
        "modified": "2003-01-17 19:15:15",
        "size": "2.32KB",
        "md5": "e70c1fb5377e0de836b2291dcac0d162",
        "sha256": "83e36d01eedf08d4903a142a602b5550bdc951877f830225c25588d916b7c871"
    },
    "Metadata": {
        "Content-Encoding": "ISO-8859-1",
        "Content-Type": "text/plain; charset=ISO-8859-1",
        "X-Parsed-By": [
            "org.apache.tika.parser.DefaultParser",
            "org.apache.tika.parser.csv.TextAndCSVParser"
        ],
        "X-TIKA:content_handler": "ToTextContentHandler",
        "X-TIKA:embedded_depth": "0",
        "X-TIKA:parse_time_millis": "1",
        "resourceName": "b'headers.h,v'"
    }
}