{
    "mios.img": {
        "modified": "2008-02-20 12:02:42",
        "size": "179.25KB",
        "md5": "ffef17b8cfbc91c44097c4dd4ff7b1d5",
        "sha256": "7069bed74a589bfd0af0e9341d223faa5d3e716fa141e2d3ddffe00d0db39590"
    },
    "Metadata": {
        "Content-Type": "application/octet-stream",
        "X-Parsed-By": "org.apache.tika.parser.EmptyParser",
        "X-TIKA:embedded_depth": "0",
        "X-TIKA:parse_time_millis": "0",
        "resourceName": "b'mios.img'"
    }
}