{
    "sdmon.elf": {
        "modified": "2008-06-25 15:22:42",
        "size": "57.67KB",
        "md5": "77a45b95a5b25013556ef0bf535252d9",
        "sha256": "13f84a6ae549c630de959836e36393464b86e55237a667aa548ac2216520dc2b"
    },
    "Metadata": {
        "Content-Type": "application/x-executable",
        "X-Parsed-By": [
            "org.apache.tika.parser.DefaultParser",
            "org.apache.tika.parser.executable.ExecutableParser"
        ],
        "X-TIKA:embedded_depth": "0",
        "X-TIKA:parse_time_millis": "1",
        "machine:architectureBits": "32",
        "machine:endian": "Big",
        "machine:machineType": "ARM",
        "machine:platform": "ARM",
        "resourceName": "b'sdmon.elf'"
    }
}