{
    "haeberli_fixed.bw,v": {
        "modified": "2005-07-12 14:09:06",
        "size": "10.12KB",
        "md5": "ab8b54ca6c133406db7da994397074a1",
        "sha256": "727f44ccc8904cbb94ca4b1f0d2c103a763430a149b2dead2393df768b6b08cd"
    },
    "Metadata": {
        "Content-Type": "application/octet-stream",
        "X-Parsed-By": "org.apache.tika.parser.EmptyParser",
        "X-TIKA:embedded_depth": "0",
        "X-TIKA:parse_time_millis": "0",
        "resourceName": "b'haeberli_fixed.bw,v'"
    }
}