{
    "bdan_grp_bda06_00.o,v": {
        "modified": "2003-10-10 23:33:52",
        "size": "19.26KB",
        "md5": "6c2ba1a8d3df7734a3c1dc6de4279b07",
        "sha256": "cae5f9a70733f4890b4c2f097baa92a4854d552857ad84fb53e07ed9e4d605c0"
    },
    "Metadata": {
        "Content-Type": "application/octet-stream",
        "X-Parsed-By": "org.apache.tika.parser.EmptyParser",
        "X-TIKA:embedded_depth": "0",
        "X-TIKA:parse_time_millis": "0",
        "resourceName": "b'bdan_grp_bda06_00.o,v'"
    }
}