{
    "INSTRUCTOR.oo,v": {
        "modified": "2003-03-18 23:41:02",
        "size": "10.7KB",
        "md5": "447fcc97bf7ed02bbaa1e043629c1ca7",
        "sha256": "7b7d68739bab25b180b1c9b360d0729a85136566ca0425915f5707d73112059e"
    },
    "Metadata": {
        "Content-Type": "application/octet-stream",
        "X-Parsed-By": "org.apache.tika.parser.EmptyParser",
        "X-TIKA:embedded_depth": "0",
        "X-TIKA:parse_time_millis": "1",
        "resourceName": "b'INSTRUCTOR.oo,v'"
    }
}