{
    "ovl_Bg_Spot01_Idohashira.szs,v": {
        "modified": "2003-02-05 19:54:20",
        "size": "2.81KB",
        "md5": "9c8f102da987bb34ae3f2a7f7bd9e0e1",
        "sha256": "cfd4a1951290cbe6f377b92e31ab92d4f0f2e4d8d4633ae52442717b154f05aa"
    },
    "Metadata": {
        "Content-Type": "application/octet-stream",
        "X-Parsed-By": "org.apache.tika.parser.EmptyParser",
        "X-TIKA:embedded_depth": "0",
        "X-TIKA:parse_time_millis": "0",
        "resourceName": "b'ovl_Bg_Spot01_Idohashira.szs,v'"
    }
}