{
    "seed52_b.imd,v": {
        "modified": "2008-09-04 05:30:44",
        "size": "9.63KB",
        "md5": "64fc62d9403adac80baad8085b158d1e",
        "sha256": "cd2ce18d9b7f371cba4aaf26fc4e77a0a0af407c695c0ac83e900cd1080c3ecf"
    },
    "Metadata": {
        "Content-Encoding": "Shift_JIS",
        "Content-Type": "text/plain; charset=Shift_JIS",
        "X-Parsed-By": [
            "org.apache.tika.parser.DefaultParser",
            "org.apache.tika.parser.csv.TextAndCSVParser"
        ],
        "X-TIKA:content_handler": "ToTextContentHandler",
        "X-TIKA:embedded_depth": "0",
        "X-TIKA:parse_time_millis": "1",
        "resourceName": "b'seed52_b.imd,v'"
    }
}