{
    "SUM_KINGYO.oo,v": {
        "modified": "2003-03-18 23:44:09",
        "size": "6.86KB",
        "md5": "30d94cf031ed77a4cc53dc7c4b848e1b",
        "sha256": "df6d80b6e2157b5ef42c2e15192096013695bb58de15b3a20f1c6580d14d2bfc"
    },
    "Metadata": {
        "Content-Type": "application/octet-stream",
        "X-Parsed-By": "org.apache.tika.parser.EmptyParser",
        "X-TIKA:embedded_depth": "0",
        "X-TIKA:parse_time_millis": "1",
        "resourceName": "b'SUM_KINGYO.oo,v'"
    }
}