{
    "ListObj.3,v": {
        "modified": "2006-02-23 14:38:28",
        "size": "10.86KB",
        "md5": "6c3e88f47fecb96f3dce5c76df710c1a",
        "sha256": "5a12aa50c21bc9460b25bc2c42cab0624497e5bcda3d18bf685d4d51c2c1f366"
    },
    "Metadata": {
        "Content-Encoding": "ISO-8859-1",
        "Content-Type": "text/plain; charset=ISO-8859-1",
        "X-Parsed-By": [
            "org.apache.tika.parser.DefaultParser",
            "org.apache.tika.parser.csv.TextAndCSVParser"
        ],
        "X-TIKA:content_handler": "ToTextContentHandler",
        "X-TIKA:embedded_depth": "0",
        "X-TIKA:parse_time_millis": "1",
        "resourceName": "b'ListObj.3,v'"
    }
}