{
    "hbm_dsmenu_eu_russian.msbt": {
        "modified": "2014-10-06 18:43:37",
        "size": "1.19KB",
        "md5": "f156622f650f4831a9b1a316cb1fc039",
        "sha256": "678a78aa96ce836a8685a46b8c501422d4262669b3e222f5d6d7f56ae75157ad"
    },
    "Metadata": {
        "Content-Type": "application/octet-stream",
        "X-Parsed-By": "org.apache.tika.parser.EmptyParser",
        "X-TIKA:embedded_depth": "0",
        "X-TIKA:parse_time_millis": "0",
        "resourceName": "b'hbm_dsmenu_eu_russian.msbt'"
    }
}