{
    "ec_porting.h": {
        "modified": "2008-03-14 11:10:36",
        "size": "5.62KB",
        "md5": "6f03a958f0d1bf06ac92ec7ee36e983c",
        "sha256": "aeb28ee2205900b0fe01c02affd88e8ccff90c98676d48866184535744b9053e"
    },
    "Metadata": {
        "Content-Encoding": "ISO-8859-1",
        "Content-Type": "text/plain; charset=ISO-8859-1",
        "X-Parsed-By": [
            "org.apache.tika.parser.DefaultParser",
            "org.apache.tika.parser.csv.TextAndCSVParser"
        ],
        "X-TIKA:content_handler": "ToTextContentHandler",
        "X-TIKA:embedded_depth": "0",
        "X-TIKA:parse_time_millis": "1",
        "resourceName": "b'ec_porting.h'"
    }
}