{
    "h_op_mono_nes.ia,v": {
        "modified": "2003-10-10 23:42:19",
        "size": "2.39KB",
        "md5": "c422764f498586b28b59beaa253e723b",
        "sha256": "f6bece4f2fc366e606d002ccf147a5e65ab9afa1dc9c3e513328ab56c00b45a8"
    },
    "Metadata": {
        "Content-Type": "application/octet-stream",
        "X-Parsed-By": "org.apache.tika.parser.EmptyParser",
        "X-TIKA:embedded_depth": "0",
        "X-TIKA:parse_time_millis": "1",
        "resourceName": "b'h_op_mono_nes.ia,v'"
    }
}