{
    "zh_point12.tex,v": {
        "modified": "2003-10-10 23:13:00",
        "size": "3.46KB",
        "md5": "d2c4542b1b96d5e2d0a3d9de99c4f953",
        "sha256": "dc03fed49fd72b47edbb041ea11738ea3367b693626312d36939ec6517f34efc"
    },
    "Metadata": {
        "Content-Encoding": "ISO-8859-1",
        "Content-Type": "text/plain; charset=ISO-8859-1",
        "X-Parsed-By": [
            "org.apache.tika.parser.DefaultParser",
            "org.apache.tika.parser.csv.TextAndCSVParser"
        ],
        "X-TIKA:content_handler": "ToTextContentHandler",
        "X-TIKA:embedded_depth": "0",
        "X-TIKA:parse_time_millis": "0",
        "resourceName": "b'zh_point12.tex,v'"
    }
}