{
    "aes-password,v": {
        "modified": "2003-06-03 12:52:35",
        "size": "0.35KB",
        "md5": "d6a3e2b66fb59f3a2cf3c7b94aae6a1d",
        "sha256": "95c11d3862e4c1f245b694f7531b62a9c08d80c3990327ca90ecfa03f4c17ef6"
    },
    "Metadata": {
        "Content-Encoding": "ISO-8859-1",
        "Content-Type": "text/plain; charset=ISO-8859-1",
        "X-Parsed-By": [
            "org.apache.tika.parser.DefaultParser",
            "org.apache.tika.parser.csv.TextAndCSVParser"
        ],
        "X-TIKA:content_handler": "ToTextContentHandler",
        "X-TIKA:embedded_depth": "0",
        "X-TIKA:parse_time_millis": "0",
        "resourceName": "b'aes-password,v'"
    }
}