{
    "font_ArchiveFont.cpp": {
        "modified": "2014-10-06 18:43:32",
        "size": "11.42KB",
        "md5": "9f317cc8910bddfb4bfee72deef36191",
        "sha256": "f9e50e820e0e116c171144611b027929b09ddaab450c4ef9ad208c8d27df3220"
    },
    "Metadata": {
        "Content-Encoding": "UTF-8",
        "Content-Type": "text/plain; charset=UTF-8",
        "X-Parsed-By": [
            "org.apache.tika.parser.DefaultParser",
            "org.apache.tika.parser.csv.TextAndCSVParser"
        ],
        "X-TIKA:content_handler": "ToTextContentHandler",
        "X-TIKA:embedded_depth": "0",
        "X-TIKA:parse_time_millis": "0",
        "resourceName": "b'font_ArchiveFont.cpp'"
    }
}