{
    "dmedia_eoe.sw,v": {
        "modified": "2003-03-08 17:47:10",
        "size": "4948.81KB",
        "md5": "4ab70fd5de08dfa2f2df9566c94db71a",
        "sha256": "a50d51442f1e1f715e2dc3a10a8b1d0b72e5862666e019b05c4b1d3baa84e3e4"
    },
    "Metadata": {
        "Content-Type": "application/octet-stream",
        "X-Parsed-By": "org.apache.tika.parser.EmptyParser",
        "X-TIKA:embedded_depth": "0",
        "X-TIKA:parse_time_millis": "1",
        "resourceName": "b'dmedia_eoe.sw,v'"
    }
}