{
    "vu.h,v": {
        "modified": "2002-10-29 01:08:10",
        "size": "3.47KB",
        "md5": "bd3f54e967e75208448367073699064f",
        "sha256": "c042aeb083e633093dfd09bb6c21dbb4572dd7e1f26874afc9108bde216fa23b"
    },
    "Metadata": {
        "Content-Encoding": "ISO-8859-1",
        "Content-Type": "text/plain; charset=ISO-8859-1",
        "X-Parsed-By": [
            "org.apache.tika.parser.DefaultParser",
            "org.apache.tika.parser.csv.TextAndCSVParser"
        ],
        "X-TIKA:content_handler": "ToTextContentHandler",
        "X-TIKA:embedded_depth": "0",
        "X-TIKA:parse_time_millis": "1",
        "resourceName": "b'vu.h,v'"
    }
}