{
    "Makefile.ssl,v": {
        "modified": "2006-02-23 14:38:32",
        "size": "32.62KB",
        "md5": "22bca1cc1375659543e4aa0a63d266d0",
        "sha256": "4c9739c37aa6066ab154ab604085b94e8e5cac101ba820a09563e9c12ef86f41"
    },
    "Metadata": {
        "Content-Encoding": "ISO-8859-1",
        "Content-Type": "text/plain; charset=ISO-8859-1",
        "X-Parsed-By": [
            "org.apache.tika.parser.DefaultParser",
            "org.apache.tika.parser.csv.TextAndCSVParser"
        ],
        "X-TIKA:content_handler": "ToTextContentHandler",
        "X-TIKA:embedded_depth": "0",
        "X-TIKA:parse_time_millis": "2",
        "resourceName": "b'Makefile.ssl,v'"
    }
}