{
    "object_hunsui.szs,v": {
        "modified": "2003-12-11 21:41:27",
        "size": "2.67KB",
        "md5": "b400cf9f1a30e672b3eec4de7a397ae5",
        "sha256": "e6ba3efc6a05d974532c4a2ba156bcb4682cce2c14bb7f3f751df6434e7d19a1"
    },
    "Metadata": {
        "Content-Type": "application/octet-stream",
        "X-Parsed-By": "org.apache.tika.parser.EmptyParser",
        "X-TIKA:embedded_depth": "0",
        "X-TIKA:parse_time_millis": "1",
        "resourceName": "b'object_hunsui.szs,v'"
    }
}