{
    "string-opt-12.c,v": {
        "modified": "2006-02-23 14:37:15",
        "size": "2.32KB",
        "md5": "5f83b0ae3c07c9a776da72e154b50620",
        "sha256": "23e286bc5689d2fc5e88404d8bb1ab142777d218147a5908771a9197aaead14d"
    },
    "Metadata": {
        "Content-Encoding": "ISO-8859-1",
        "Content-Type": "text/plain; charset=ISO-8859-1",
        "X-Parsed-By": [
            "org.apache.tika.parser.DefaultParser",
            "org.apache.tika.parser.csv.TextAndCSVParser"
        ],
        "X-TIKA:content_handler": "ToTextContentHandler",
        "X-TIKA:embedded_depth": "0",
        "X-TIKA:parse_time_millis": "1",
        "resourceName": "b'string-opt-12.c,v'"
    }
}