{
    "Overview.html": {
        "modified": "2011-09-30 15:06:00",
        "size": "2.47KB",
        "md5": "943c0f05b4b17e744014e46a0721a24d",
        "sha256": "4e5fa341dea1218148a88ef84b28c5d49db1b765b9a2c917adf5e9341e2b876f"
    },
    "Metadata": {
        "Content-Encoding": "UTF-8",
        "Content-Language": "ja",
        "Content-Style-Type": "text/css",
        "Content-Type": "application/xhtml+xml; charset=UTF-8",
        "Content-Type-Hint": "text/html; charset=utf-8",
        "X-Parsed-By": [
            "org.apache.tika.parser.DefaultParser",
            "org.apache.tika.parser.html.HtmlParser"
        ],
        "X-TIKA:content_handler": "ToTextContentHandler",
        "X-TIKA:embedded_depth": "0",
        "X-TIKA:parse_time_millis": "1",
        "dc:title": "nn::y2r",
        "resourceName": "b'Overview.html'",
        "title": "nn::y2r"
    }
}