{
    "field_demo.c,v": {
        "modified": "2008-09-04 05:30:46",
        "size": "173.35KB",
        "md5": "1b2eb3a2aa747a7cfc4255a2c46647e4",
        "sha256": "817d6ff85d6db4078913adfb7d7d5de76aade0037ff59ad12c4b856f3802deb8"
    },
    "Metadata": {
        "Content-Encoding": "Shift_JIS",
        "Content-Type": "text/plain; charset=Shift_JIS",
        "X-Parsed-By": [
            "org.apache.tika.parser.DefaultParser",
            "org.apache.tika.parser.csv.TextAndCSVParser"
        ],
        "X-TIKA:content_handler": "ToTextContentHandler",
        "X-TIKA:embedded_depth": "0",
        "X-TIKA:parse_time_millis": "3",
        "resourceName": "b'field_demo.c,v'"
    }
}