{
    "m_dun1001_00_01a.dat,v": {
        "modified": "2008-09-04 05:30:10",
        "size": "6.24KB",
        "md5": "50f5ffe19a4eab969343a5093bad2ae3",
        "sha256": "c8f317bac25f055b3315fa6a6191d9db6f2ccb4e286c6244bcb4403c955a327e"
    },
    "Metadata": {
        "Content-Type": "application/octet-stream",
        "X-Parsed-By": "org.apache.tika.parser.EmptyParser",
        "X-TIKA:embedded_depth": "0",
        "X-TIKA:parse_time_millis": "1",
        "resourceName": "b'm_dun1001_00_01a.dat,v'"
    }
}