{
    "gtkhscale.h,v": {
        "modified": "2006-02-23 14:39:39",
        "size": "3.03KB",
        "md5": "3e32d45f00abb6b0482133f9024464eb",
        "sha256": "13340195fdd6a18552d4113f9a2109c7ff4e567f2a7d0f110bb4ddac537583a7"
    },
    "Metadata": {
        "Content-Encoding": "ISO-8859-1",
        "Content-Type": "text/plain; charset=ISO-8859-1",
        "X-Parsed-By": [
            "org.apache.tika.parser.DefaultParser",
            "org.apache.tika.parser.csv.TextAndCSVParser"
        ],
        "X-TIKA:content_handler": "ToTextContentHandler",
        "X-TIKA:embedded_depth": "0",
        "X-TIKA:parse_time_millis": "1",
        "resourceName": "b'gtkhscale.h,v'"
    }
}