{
    "TFSDL0P.126": {
        "modified": "1994-05-26 15:00:56",
        "size": "32.0KB",
        "md5": "4c7825dda2ef0520aae563e69134c11d",
        "sha256": "bb341cc02e39fa35d78bab56523ae67b9ef61d93ec7d752304e25e8767c07ae9"
    },
    "Metadata": {
        "Content-Type": "application/octet-stream",
        "X-Parsed-By": "org.apache.tika.parser.EmptyParser",
        "X-TIKA:embedded_depth": "0",
        "X-TIKA:parse_time_millis": "1",
        "resourceName": "b'TFSDL0P.126'"
    }
}