{
    "bulkusr.h,v": {
        "modified": "2009-03-24 18:25:04",
        "size": "9.11KB",
        "md5": "524154f62958cdc2602bffef9752f1ad",
        "sha256": "6ef618928408257a620ba959046bab52b6a8cdb3838e1d20ed2b865fc7fd6739"
    },
    "Metadata": {
        "Content-Encoding": "windows-1252",
        "Content-Type": "text/tsv; charset=windows-1252; delimiter=tab",
        "X-Parsed-By": [
            "org.apache.tika.parser.DefaultParser",
            "org.apache.tika.parser.csv.TextAndCSVParser"
        ],
        "X-TIKA:content_handler": "ToTextContentHandler",
        "X-TIKA:embedded_depth": "0",
        "X-TIKA:parse_time_millis": "1",
        "csv:delimiter": "tab",
        "resourceName": "b'bulkusr.h,v'"
    }
}