{
    "curve_parameters_fp.h": {
        "modified": "2014-10-06 18:48:30",
        "size": "21.14KB",
        "md5": "5643647b044c4632cb6a7411edfd0d44",
        "sha256": "1d7c84548520c7c2ecdf8a93de89487dff962650cf3e0354a4dd22621c4c6c40"
    },
    "Metadata": {
        "Content-Encoding": "windows-1252",
        "Content-Type": "text/plain; charset=windows-1252",
        "X-Parsed-By": [
            "org.apache.tika.parser.DefaultParser",
            "org.apache.tika.parser.csv.TextAndCSVParser"
        ],
        "X-TIKA:content_handler": "ToTextContentHandler",
        "X-TIKA:embedded_depth": "0",
        "X-TIKA:parse_time_millis": "1",
        "resourceName": "b'curve_parameters_fp.h'"
    }
}