{
    "link_anchor_defense_long_hitL.o,v": {
        "modified": "2003-10-10 23:33:19",
        "size": "2.5KB",
        "md5": "44476a86ef7b2a4942c306b8c5bda87d",
        "sha256": "1644b3e777e8df5f399c52e987d79bda80ba3f3f31ed5bea1203290becdf8aa7"
    },
    "Metadata": {
        "Content-Type": "application/octet-stream",
        "X-Parsed-By": "org.apache.tika.parser.EmptyParser",
        "X-TIKA:embedded_depth": "0",
        "X-TIKA:parse_time_millis": "0",
        "resourceName": "b'link_anchor_defense_long_hitL.o,v'"
    }
}