{
    "bailey03.psd,v": {
        "modified": "2004-03-05 15:20:29",
        "size": "14.75KB",
        "md5": "a270684d1d2a3cad3471c896f6111e70",
        "sha256": "4d5ad67f067aafba026a4bc7f9e30d566e462e8e9f9e076cb695d0d77dce03d2"
    },
    "Metadata": {
        "Content-Type": "application/octet-stream",
        "X-Parsed-By": "org.apache.tika.parser.EmptyParser",
        "X-TIKA:embedded_depth": "0",
        "X-TIKA:parse_time_millis": "0",
        "resourceName": "b'bailey03.psd,v'"
    }
}