{
    "MillerTo.GSM,v": {
        "modified": "2004-03-05 15:18:33",
        "size": "0.56KB",
        "md5": "bae142af452b25949569f32b37b86328",
        "sha256": "28cd6730be936927753d5be3834921b89eb26c0de9805b126d9665e26ef5a212"
    },
    "Metadata": {
        "Content-Type": "application/octet-stream",
        "X-Parsed-By": "org.apache.tika.parser.EmptyParser",
        "X-TIKA:embedded_depth": "0",
        "X-TIKA:parse_time_millis": "1",
        "resourceName": "b'MillerTo.GSM,v'"
    }
}