{
    "fads.h,v": {
        "modified": "2006-02-23 14:38:58",
        "size": "2.8KB",
        "md5": "e350e930b8b4037540d355858c07e3d8",
        "sha256": "e0e6368b683359355694508d4acad91e23411a846cec1eaa88b64bb18f0e48ea"
    },
    "Metadata": {
        "Content-Encoding": "ISO-8859-1",
        "Content-Type": "text/plain; charset=ISO-8859-1",
        "X-Parsed-By": [
            "org.apache.tika.parser.DefaultParser",
            "org.apache.tika.parser.csv.TextAndCSVParser"
        ],
        "X-TIKA:content_handler": "ToTextContentHandler",
        "X-TIKA:embedded_depth": "0",
        "X-TIKA:parse_time_millis": "1",
        "resourceName": "b'fads.h,v'"
    }
}