{
    "opsRolesDetail.xsl,v": {
        "modified": "2006-08-15 19:34:20",
        "size": "6.52KB",
        "md5": "1da1d04642a42cabf0cfe791df723555",
        "sha256": "017d5cca11cbdfa27754412c3c7f1766981a75493a2f3665e6c8ab09b42d91f4"
    },
    "Metadata": {
        "Content-Encoding": "windows-1252",
        "Content-Type": "text/plain; charset=windows-1252",
        "X-Parsed-By": [
            "org.apache.tika.parser.DefaultParser",
            "org.apache.tika.parser.csv.TextAndCSVParser"
        ],
        "X-TIKA:content_handler": "ToTextContentHandler",
        "X-TIKA:embedded_depth": "0",
        "X-TIKA:parse_time_millis": "0",
        "resourceName": "b'opsRolesDetail.xsl,v'"
    }
}