{
    "scc.c,v": {
        "modified": "2006-02-23 14:39:03",
        "size": "55.35KB",
        "md5": "875b63ec272c96afef8258b128a75813",
        "sha256": "53b906c72e8b8812d624b0aecf9ed1477fde8b5202f3b744045e43f7f169d58e"
    },
    "Metadata": {
        "Content-Encoding": "ISO-8859-1",
        "Content-Type": "text/plain; charset=ISO-8859-1",
        "X-Parsed-By": [
            "org.apache.tika.parser.DefaultParser",
            "org.apache.tika.parser.csv.TextAndCSVParser"
        ],
        "X-TIKA:content_handler": "ToTextContentHandler",
        "X-TIKA:embedded_depth": "0",
        "X-TIKA:parse_time_millis": "1",
        "resourceName": "b'scc.c,v'"
    }
}