{
    "msd-l1.gpi,v": {
        "modified": "2009-03-13 14:22:15",
        "size": "2.63KB",
        "md5": "3528cafb674e9ddf001be3422d2aedbb",
        "sha256": "60ef6af0a96704948d8823a0f0ab871c31d8aaa325009421b04d42f9d94bbf7c"
    },
    "Metadata": {
        "Content-Encoding": "ISO-8859-1",
        "Content-Type": "text/plain; charset=ISO-8859-1",
        "X-Parsed-By": [
            "org.apache.tika.parser.DefaultParser",
            "org.apache.tika.parser.csv.TextAndCSVParser"
        ],
        "X-TIKA:content_handler": "ToTextContentHandler",
        "X-TIKA:embedded_depth": "0",
        "X-TIKA:parse_time_millis": "1",
        "resourceName": "b'msd-l1.gpi,v'"
    }
}