{
    "lex_config.l,v": {
        "modified": "2006-02-23 14:38:47",
        "size": "7.59KB",
        "md5": "b144fb22b372bd57b7f907f4ac555eb0",
        "sha256": "d97466c9e52bbb8c73b3c7a9d3d8b022210b604737909cea90eaa0b7f3391093"
    },
    "Metadata": {
        "Content-Encoding": "ISO-8859-1",
        "Content-Type": "text/plain; charset=ISO-8859-1",
        "X-Parsed-By": [
            "org.apache.tika.parser.DefaultParser",
            "org.apache.tika.parser.csv.TextAndCSVParser"
        ],
        "X-TIKA:content_handler": "ToTextContentHandler",
        "X-TIKA:embedded_depth": "0",
        "X-TIKA:parse_time_millis": "1",
        "resourceName": "b'lex_config.l,v'"
    }
}