{
    "m_Hwat00_Down.o,v": {
        "modified": "2003-01-17 13:13:57",
        "size": "2.94KB",
        "md5": "50b87af0694d4e332e757373b34d574d",
        "sha256": "f59bee316f32c997e8e1ab9ef44c4e6840d0df04850e6e9101885af15f528a72"
    },
    "Metadata": {
        "Content-Type": "application/octet-stream",
        "X-Parsed-By": "org.apache.tika.parser.EmptyParser",
        "X-TIKA:embedded_depth": "0",
        "X-TIKA:parse_time_millis": "1",
        "resourceName": "b'm_Hwat00_Down.o,v'"
    }
}