{
    "bdanDD_9_shape.o,v": {
        "modified": "2003-10-10 23:33:55",
        "size": "1.68KB",
        "md5": "08c681a5d11d473ac1b82b9ac57918df",
        "sha256": "315c1d5e5198908421214755eb765c0a87775afca283d8bf1fefe64d3c697d5d"
    },
    "Metadata": {
        "Content-Type": "application/octet-stream",
        "X-Parsed-By": "org.apache.tika.parser.EmptyParser",
        "X-TIKA:embedded_depth": "0",
        "X-TIKA:parse_time_millis": "0",
        "resourceName": "b'bdanDD_9_shape.o,v'"
    }
}