{
    "GXManage.h": {
        "modified": "2005-12-29 15:53:28",
        "size": "0.65KB",
        "md5": "5c2cfdee4895582baecebcf52f1e71ff",
        "sha256": "fd10bd7f0fb9362c963728c9886ccc7dd71000769b4ba5d9ce6e024f1367f2c3"
    },
    "Metadata": {
        "Content-Encoding": "windows-1252",
        "Content-Type": "text/plain; charset=windows-1252",
        "X-Parsed-By": [
            "org.apache.tika.parser.DefaultParser",
            "org.apache.tika.parser.csv.TextAndCSVParser"
        ],
        "X-TIKA:content_handler": "ToTextContentHandler",
        "X-TIKA:embedded_depth": "0",
        "X-TIKA:parse_time_millis": "0",
        "resourceName": "b'GXManage.h'"
    }
}