{
    "ResetDrawCharCount.html": {
        "modified": "2011-09-30 15:04:26",
        "size": "1.41KB",
        "md5": "83ecc681c68b1b9aa8549aa63613e2f8",
        "sha256": "85a8092ad3f7931bb2135da33a3528b6642b1d9cf711b7c9695adea566627c07"
    },
    "Metadata": {
        "Content-Encoding": "UTF-8",
        "Content-Language": "ja",
        "Content-Style-Type": "text/css",
        "Content-Type": "application/xhtml+xml; charset=UTF-8",
        "Content-Type-Hint": "text/html; charset=utf-8",
        "X-Parsed-By": [
            "org.apache.tika.parser.DefaultParser",
            "org.apache.tika.parser.html.HtmlParser"
        ],
        "X-TIKA:content_handler": "ToTextContentHandler",
        "X-TIKA:embedded_depth": "0",
        "X-TIKA:parse_time_millis": "1",
        "dc:title": "ResetDrawCharCount",
        "resourceName": "b'ResetDrawCharCount.html'",
        "title": "ResetDrawCharCount"
    }
}