{
    "dpnor1021.vmd,v": {
        "modified": "2002-10-29 01:03:12",
        "size": "1.81KB",
        "md5": "7e21aba1a92a5f5dfabe9398cd9bb29e",
        "sha256": "aa3369bdb4726ab1b8ba57469a1f593c6c72acfc88cac5cdcdf7d7c790fb5ead"
    },
    "Metadata": {
        "Content-Encoding": "ISO-8859-1",
        "Content-Type": "text/plain; charset=ISO-8859-1",
        "X-Parsed-By": [
            "org.apache.tika.parser.DefaultParser",
            "org.apache.tika.parser.csv.TextAndCSVParser"
        ],
        "X-TIKA:content_handler": "ToTextContentHandler",
        "X-TIKA:embedded_depth": "0",
        "X-TIKA:parse_time_millis": "1",
        "resourceName": "b'dpnor1021.vmd,v'"
    }
}