{
    "fox_15252.y.44.c4.aiff,v": {
        "modified": "2003-11-13 15:02:28",
        "size": "246.28KB",
        "md5": "9457bb5d6a8164e9edb3264fa9ca00bc",
        "sha256": "15a238c62c45ac8c63d870d24fa09ba19bdeca6385cf150439ab183e35d56a32"
    },
    "Metadata": {
        "Content-Type": "application/octet-stream",
        "X-Parsed-By": "org.apache.tika.parser.EmptyParser",
        "X-TIKA:embedded_depth": "0",
        "X-TIKA:parse_time_millis": "0",
        "resourceName": "b'fox_15252.y.44.c4.aiff,v'"
    }
}