{
    "rdp_output_len.c,v": {
        "modified": "2005-07-12 14:09:46",
        "size": "2.75KB",
        "md5": "f2a238b0a6d3e44200fb7c34d040a65c",
        "sha256": "942e3404886d882e9c3c2789cda2900e4163920e8bb87ab82d6d0223c0b61365"
    },
    "Metadata": {
        "Content-Encoding": "ISO-8859-1",
        "Content-Type": "text/plain; charset=ISO-8859-1",
        "X-Parsed-By": [
            "org.apache.tika.parser.DefaultParser",
            "org.apache.tika.parser.csv.TextAndCSVParser"
        ],
        "X-TIKA:content_handler": "ToTextContentHandler",
        "X-TIKA:embedded_depth": "0",
        "X-TIKA:parse_time_millis": "1",
        "resourceName": "b'rdp_output_len.c,v'"
    }
}