{
    "_frake_eat.c,v": {
        "modified": "2004-12-08 16:20:26",
        "size": "0.83KB",
        "md5": "b6e0bacc243a29f3bd7feb2dade610df",
        "sha256": "3fc6c66be678a65621b7247a82a5c2113000945080f1d851bcd80692099a6eab"
    },
    "Metadata": {
        "Content-Encoding": "ISO-8859-1",
        "Content-Type": "text/plain; charset=ISO-8859-1",
        "X-Parsed-By": [
            "org.apache.tika.parser.DefaultParser",
            "org.apache.tika.parser.csv.TextAndCSVParser"
        ],
        "X-TIKA:content_handler": "ToTextContentHandler",
        "X-TIKA:embedded_depth": "0",
        "X-TIKA:parse_time_millis": "1",
        "resourceName": "b'_frake_eat.c,v'"
    }
}