{
    "d28r0103.gmm,v": {
        "modified": "2007-06-12 21:40:42",
        "size": "33.76KB",
        "md5": "678304872683fbb1bc852d961f9a4a80",
        "sha256": "b93a5fdd92dec3b1dc92fbe04deba3b27b3f13383c617aff0214506989883308"
    },
    "Metadata": {
        "Content-Type": "application/octet-stream",
        "X-Parsed-By": "org.apache.tika.parser.EmptyParser",
        "X-TIKA:embedded_depth": "0",
        "X-TIKA:parse_time_millis": "1",
        "resourceName": "b'd28r0103.gmm,v'"
    }
}